ConstrainedKMeans/ConstrainedKMeans.py
ConstrainedKMeans/__init__.py
ConstrainedKMeans/example.py
ConstrainedKMeans-1.2.dist-info/LICENCE
ConstrainedKMeans-1.2.dist-info/METADATA
ConstrainedKMeans-1.2.dist-info/WHEEL
ConstrainedKMeans-1.2.dist-info/top_level.txt
ConstrainedKMeans-1.2.dist-info/RECORD
