Metadata-Version: 2.1
Name: ConstrainedKMeans
Version: 1.2
Summary: A constrained KMeans algorithm.
Home-page: https://github.com/ferrocactus/ConstrainedKMeans
Author: Euxhen Hasanaj
Author-email: ehasanaj@cs.cmu.edu
License: UNKNOWN
Platform: UNKNOWN
Classifier: Programming Language :: Python :: 3
Classifier: License :: OSI Approved :: MIT License
Classifier: Operating System :: OS Independent
Requires-Python: >=3.7
Requires-Dist: matplotlib
Requires-Dist: numpy
Requires-Dist: scipy
